fixedrec/bsd_checksum.py
fixedrec/fixedrec.py
fixedrec/layout.py
fixedrec/record.py
fixedrec/rectypes.py
fixedrec/utils.py
fixedrec/__init__.py
fixedrec-1.0.3.dist-info/DESCRIPTION.rst
fixedrec-1.0.3.dist-info/METADATA
fixedrec-1.0.3.dist-info/metadata.json
fixedrec-1.0.3.dist-info/RECORD
fixedrec-1.0.3.dist-info/top_level.txt
fixedrec-1.0.3.dist-info/WHEEL
