Metadata-Version: 2.0
Name: fixedrec
Version: 1.0.3
Summary: fixedrec - Fixed size record IO
Home-page: https://github.com/thebjorn/fixedrec
Author: Bjorn Pettersen
Author-email: bp@norsktest.no
License: UNKNOWN
Platform: UNKNOWN
Classifier: Development Status :: 3 - Alpha
Classifier: Intended Audience :: Developers
Classifier: Programming Language :: Python
Classifier: Programming Language :: Python :: 2
Classifier: Programming Language :: Python :: 2.7
Classifier: Programming Language :: Python :: 3
Classifier: Programming Language :: Python :: 3.4
Classifier: Topic :: Software Development :: Libraries
